.git-hash
MANIFEST.in
README.md
setup.cfg
setup.py
src/cm_api/__init__.py
src/cm_api/api_client.py
src/cm_api/http_client.py
src/cm_api/resource.py
src/cm_api.egg-info/PKG-INFO
src/cm_api.egg-info/SOURCES.txt
src/cm_api.egg-info/dependency_links.txt
src/cm_api.egg-info/entry_points.txt
src/cm_api.egg-info/requires.txt
src/cm_api.egg-info/top_level.txt
src/cm_api.egg-info/zip-safe
src/cm_api/endpoints/__init__.py
src/cm_api/endpoints/batch.py
src/cm_api/endpoints/clusters.py
src/cm_api/endpoints/cms.py
src/cm_api/endpoints/dashboards.py
src/cm_api/endpoints/events.py
src/cm_api/endpoints/external_accounts.py
src/cm_api/endpoints/host_templates.py
src/cm_api/endpoints/hosts.py
src/cm_api/endpoints/parcels.py
src/cm_api/endpoints/role_config_groups.py
src/cm_api/endpoints/roles.py
src/cm_api/endpoints/services.py
src/cm_api/endpoints/timeseries.py
src/cm_api/endpoints/tools.py
src/cm_api/endpoints/types.py
src/cm_api/endpoints/users.py
src/cm_shell/__init__.py
src/cm_shell/cmps.py
src/cm_shell/prettytable.py